osconfiglib/__init__.py
osconfiglib/cli/__init__.py
osconfiglib/cli/main.py
osconfiglib/layers.py
osconfiglib/utils.py
osconfiglib/virt_customize.py
osconfiglib-0.2.1.dist-info/entry_points.txt
osconfiglib-0.2.1.dist-info/WHEEL
osconfiglib-0.2.1.dist-info/METADATA
osconfiglib-0.2.1.dist-info/RECORD
